napari_mlarray/__init__.py
napari_mlarray/_reader.py
napari_mlarray/_version.py
napari_mlarray/_widget.py
napari_mlarray/_writer.py
napari_mlarray/napari.yaml
napari_mlarray-0.0.2.dist-info/licenses/LICENSE
napari_mlarray-0.0.2.dist-info/METADATA
napari_mlarray-0.0.2.dist-info/WHEEL
napari_mlarray-0.0.2.dist-info/entry_points.txt
napari_mlarray-0.0.2.dist-info/top_level.txt
napari_mlarray-0.0.2.dist-info/RECORD
