Metadata-Version: 2.4
Name: napari-mlarray
Version: 0.0.2
Summary: A reader/writer Napari plugin for MLArray images.
Author: Karol-G
Author-email: karol.gotkowski@dkfz.de
License: 
Classifier: Development Status :: 2 - Pre-Alpha
Classifier: Framework :: napari
Classifier: Intended Audience :: Developers
Classifier: License :: OSI Approved :: MIT License
Classifier: Operating System :: OS Independent
Classifier: Programming Language :: Python
Classifier: Programming Language :: Python :: 3
Classifier: Programming Language :: Python :: 3 :: Only
Classifier: Programming Language :: Python :: 3.10
Classifier: Programming Language :: Python :: 3.11
Classifier: Programming Language :: Python :: 3.12
Classifier: Programming Language :: Python :: 3.13
Classifier: Topic :: Scientific/Engineering :: Image Processing
Requires-Python: >=3.10
License-File: LICENSE
Requires-Dist: mlarray
Requires-Dist: numpy
Provides-Extra: all
Requires-Dist: napari[all]; extra == "all"
Dynamic: license-file
